WuaiPojieLuntanjinghuaJi2013Fix1/README.md
WuaiPojieLuntanjinghuaJi2013Fix1/__init__.py
WuaiPojieLuntanjinghuaJi2013Fix1/__main__.py
WuaiPojieLuntanjinghuaJi2013Fix1/file.epub
WuaiPojieLuntanjinghuaJi2013Fix1/index.html
WuaiPojieLuntanjinghuaJi2013Fix1/css/__init__.py
WuaiPojieLuntanjinghuaJi2013Fix1/css/annotations.css
WuaiPojieLuntanjinghuaJi2013Fix1/css/main.css
WuaiPojieLuntanjinghuaJi2013Fix1/css/normalize.css
WuaiPojieLuntanjinghuaJi2013Fix1/css/popup.css
WuaiPojieLuntanjinghuaJi2013Fix1/font/__init__.py
WuaiPojieLuntanjinghuaJi2013Fix1/font/fontello.eot
WuaiPojieLuntanjinghuaJi2013Fix1/font/fontello.svg
WuaiPojieLuntanjinghuaJi2013Fix1/font/fontello.ttf
WuaiPojieLuntanjinghuaJi2013Fix1/font/fontello.woff
WuaiPojieLuntanjinghuaJi2013Fix1/img/__init__.py
WuaiPojieLuntanjinghuaJi2013Fix1/img/annotator-glyph-sprite.png
WuaiPojieLuntanjinghuaJi2013Fix1/img/annotator-icon-sprite.png
WuaiPojieLuntanjinghuaJi2013Fix1/img/apple-touch-icon.png
WuaiPojieLuntanjinghuaJi2013Fix1/img/cancelfullscreen.png
WuaiPojieLuntanjinghuaJi2013Fix1/img/close.png
WuaiPojieLuntanjinghuaJi2013Fix1/img/fullscreen.png
WuaiPojieLuntanjinghuaJi2013Fix1/img/loader.gif
WuaiPojieLuntanjinghuaJi2013Fix1/img/menu-icon.png
WuaiPojieLuntanjinghuaJi2013Fix1/img/save.png
WuaiPojieLuntanjinghuaJi2013Fix1/img/saved.png
WuaiPojieLuntanjinghuaJi2013Fix1/img/settings-s.png
WuaiPojieLuntanjinghuaJi2013Fix1/img/settings.png
WuaiPojieLuntanjinghuaJi2013Fix1/img/star.png
WuaiPojieLuntanjinghuaJi2013Fix1/js/__init__.py
WuaiPojieLuntanjinghuaJi2013Fix1/js/epub.js
WuaiPojieLuntanjinghuaJi2013Fix1/js/epub.min.js
WuaiPojieLuntanjinghuaJi2013Fix1/js/epub.min.map
WuaiPojieLuntanjinghuaJi2013Fix1/js/hooks.min.js
WuaiPojieLuntanjinghuaJi2013Fix1/js/hooks.min.map
WuaiPojieLuntanjinghuaJi2013Fix1/js/reader.js
WuaiPojieLuntanjinghuaJi2013Fix1/js/reader.js.map
WuaiPojieLuntanjinghuaJi2013Fix1/js/reader.min.js
WuaiPojieLuntanjinghuaJi2013Fix1/js/reader.min.map
WuaiPojieLuntanjinghuaJi2013Fix1/js/hooks/__init__.py
wuai_pojie_luntanjinghua_ji_2013_fix1-2025.3.25.0.dist-info/METADATA
wuai_pojie_luntanjinghua_ji_2013_fix1-2025.3.25.0.dist-info/WHEEL
wuai_pojie_luntanjinghua_ji_2013_fix1-2025.3.25.0.dist-info/entry_points.txt
wuai_pojie_luntanjinghua_ji_2013_fix1-2025.3.25.0.dist-info/top_level.txt
wuai_pojie_luntanjinghua_ji_2013_fix1-2025.3.25.0.dist-info/RECORD
